pymyinstall/__init__.py
pymyinstall/__main__.py
pymyinstall/cli/__init__.py
pymyinstall/cli/pymy_deps.py
pymyinstall/cli/pymy_install.py
pymyinstall/cli/pymy_status.py
pymyinstall/cli/pymy_update.py
pymyinstall/fix/__init__.py
pymyinstall/fix/releases.py
pymyinstall/fix/win32py37.py
pymyinstall/installcustom/__init__.py
pymyinstall/installcustom/install_custom.py
pymyinstall/installcustom/install_custom_7z.py
pymyinstall/installcustom/install_custom_R.py
pymyinstall/installcustom/install_custom_chromedriver.py
pymyinstall/installcustom/install_custom_exceptions.py
pymyinstall/installcustom/install_custom_git.py
pymyinstall/installcustom/install_custom_graphviz.py
pymyinstall/installcustom/install_custom_inkscape.py
pymyinstall/installcustom/install_custom_javajdk.py
pymyinstall/installcustom/install_custom_jenkins.py
pymyinstall/installcustom/install_custom_julia.py
pymyinstall/installcustom/install_custom_miktex.py
pymyinstall/installcustom/install_custom_mingw.py
pymyinstall/installcustom/install_custom_operadriver.py
pymyinstall/installcustom/install_custom_pandoc.py
pymyinstall/installcustom/install_custom_putty.py
pymyinstall/installcustom/install_custom_python.py
pymyinstall/installcustom/install_custom_revealjs.py
pymyinstall/installcustom/install_custom_sbt.py
pymyinstall/installcustom/install_custom_scite.py
pymyinstall/installcustom/install_custom_sqlitespy.py
pymyinstall/installcustom/install_custom_tdm_gcc.py
pymyinstall/installcustom/install_custom_vs.py
pymyinstall/installhelper/__init__.py
pymyinstall/installhelper/get_pip.py
pymyinstall/installhelper/install_cmd_helper.py
pymyinstall/installhelper/install_cmd_regex.py
pymyinstall/installhelper/install_manual.py
pymyinstall/installhelper/install_memoize.py
pymyinstall/installhelper/install_venv_helper.py
pymyinstall/installhelper/internet_settings.py
pymyinstall/installhelper/link_shortcuts.py
pymyinstall/installhelper/missing_license.py
pymyinstall/installhelper/module_dependencies.py
pymyinstall-1.4.1958.dist-info/LICENSE.txt
pymyinstall-1.4.1958.dist-info/METADATA
pymyinstall-1.4.1958.dist-info/WHEEL
pymyinstall-1.4.1958.dist-info/entry_points.txt
pymyinstall-1.4.1958.dist-info/top_level.txt
pymyinstall-1.4.1958.dist-info/RECORD
