Metadata-Version: 2.1
Name: pymyinstall
Version: 1.4.1958
Summary: Easy installation of modules for data scientists
Home-page: http://www.xavierdupre.fr/app/pymyinstall/helpsphinx/index.html
Author: Xavier Dupré
Author-email: xavier.dupre@gmail.com
License: MIT
Download-URL: https://github.com/sdpython/pymyinstall/
Keywords: pymyinstall,installation,Xavier Dupré
Platform: UNKNOWN
Classifier: Programming Language :: Python :: 3
Classifier: Intended Audience :: Developers
Classifier: Topic :: Scientific/Engineering
Classifier: Topic :: Education
Classifier: License :: OSI Approved :: MIT License
Classifier: Development Status :: 5 - Production/Stable
Requires-Dist: setuptools
Requires-Dist: pip (>=10.0)
Requires-Dist: urllib3
Requires-Dist: requests
